maxlib/__init__.py
maxlib/collect.py
maxlib/currency.py
maxlib/db.py
maxlib/portfolio.py
maxlib/utils.py
maxlib_repackaged_MGGY8411_yy2205-0.1.3.dist-info/METADATA
maxlib_repackaged_MGGY8411_yy2205-0.1.3.dist-info/WHEEL
maxlib_repackaged_MGGY8411_yy2205-0.1.3.dist-info/top_level.txt
maxlib_repackaged_MGGY8411_yy2205-0.1.3.dist-info/RECORD
