Metadata-Version: 2.1
Name: maxlib-repackaged-MGGY8411-yy2205
Version: 0.1.3
Summary: Max's code repackaged as a library
Author: Yue
Author-email: yy2205@nyu.edu
Requires-Dist: wheel
Requires-Dist: pandas
Requires-Dist: matplotlib
Requires-Dist: numpy
Requires-Dist: sqlalchemy
Requires-Dist: jupyter
Requires-Dist: polygon-api-client
